minisentry/__init__.py
minisentry/admin.py
minisentry/apps.py
minisentry/models.py
minisentry/urls.py
minisentry/views.py
minisentry/migrations/0001_initial.py
minisentry/migrations/__init__.py
minisentry/templates/minisentry/show.html
minisentry/templatetags/__init__.py
minisentry/templatetags/minisentry_extra.py
django_minisentry-20240206.1.dist-info/LICENSE
django_minisentry-20240206.1.dist-info/METADATA
django_minisentry-20240206.1.dist-info/WHEEL
django_minisentry-20240206.1.dist-info/top_level.txt
django_minisentry-20240206.1.dist-info/RECORD
