Metadata-Version: 2.1
Name: django-minisentry
Version: 20240206.1
Summary: A Django app to collect sentry errors in local database, render in a simplified UI similar to Sentry
Home-page: https://github.com/bartekbrak/django-minisentry
Author: Bartek Brak
Author-email: bartek@brak.dev
License: BSD-3-Clause
Classifier: Environment :: Web Environment
Classifier: Framework :: Django
Classifier: Framework :: Django :: 4.1
Classifier: Intended Audience :: Developers
Classifier: License :: OSI Approved :: BSD License
Classifier: Operating System :: OS Independent
Classifier: Programming Language :: Python
Classifier: Programming Language :: Python :: 3
Classifier: Programming Language :: Python :: 3 :: Only
Classifier: Programming Language :: Python :: 3.6
Classifier: Topic :: Internet :: WWW/HTTP
Classifier: Topic :: Internet :: WWW/HTTP :: Dynamic Content
Requires-Python: >=3.6
License-File: LICENSE
Requires-Dist: Django >=4.1
